MANIFEST.in
README.md
setup.py
games/.gitignore
games/__init__.py
games/1000 Miglia/metadata.ini
games/1000 Miglia/title.png
games/10th Frame/metadata.ini
games/10th Frame/title.png
games/1830/metadata.ini
games/1830/title.png
games/1869/metadata.ini
games/1869/title.png
games/1942 - The Pacific Air War/metadata.ini
games/1942 - The Pacific Air War/title.png
games/1994Pool/metadata.ini
games/1994Pool/title.png
games/1995 Card Game/metadata.ini
games/1995 Card Game/title.png
games/20,000 Leagues Under the Sea/metadata.ini
games/20,000 Leagues Under the Sea/title.png
games/21 for 1 to 4/metadata.ini
games/21 for 1 to 4/title.png
games/221B Baker St/metadata.ini
games/221B Baker St/title.png
games/240 Racing/metadata.ini
games/240 Racing/title.png
games/2400 A.D./metadata.ini
games/2400 A.D./title.png
games/3-Demon/metadata.ini
games/3-Demon/title.png
games/3D Body Adventure/metadata.ini
games/3D Body Adventure/title.png
games/3D Bomber/metadata.ini
games/3D Bomber/title.png
games/3D Cyberpuck/metadata.ini
games/3D Cyberpuck/title.png
games/3D TableSports/metadata.ini
games/3D TableSports/title.png
games/3D World Boxing/metadata.ini
games/3D World Boxing/title.png
games/3D World Tennis/metadata.ini
games/3D World Tennis/title.png
games/4 Queens Computer Casino/metadata.ini
games/4 Queens Computer Casino/title.png
games/4x4 Off Road Racing/metadata.ini
games/4x4 Off Road Racing/title.png
games/4x4 Team/metadata.ini
games/4x4 Team/title.png
games/5th Fleet/metadata.ini
games/5th Fleet/title.png
games/688 Attack Sub/metadata.ini
games/688 Attack Sub/title.png
games/7 Colors/metadata.ini
games/7 Colors/title.png
games/A Train/metadata.ini
games/A Train/title.png
games/A.G.E./metadata.ini
games/A.G.E./title.png
games/A.J.'s World of Discovery/metadata.ini
games/A.J.'s World of Discovery/title.png
games/A10 Tank Killer (1)/metadata.ini
games/A10 Tank Killer (1)/title.png
games/A10 Tank Killer (2)/metadata.ini
games/A10 Tank Killer (2)/title.png
ialauncher.egg-info/PKG-INFO
ialauncher.egg-info/SOURCES.txt
ialauncher.egg-info/dependency_links.txt
ialauncher.egg-info/entry_points.txt
ialauncher.egg-info/requires.txt
ialauncher.egg-info/top_level.txt