Metadata-Version: 2.1
Name: ialauncher
Version: 2.2.1
Summary: A DOSBox frontend for the Internet Archive
Home-page: https://ialauncher.created.today/
Author: Jaap Joris Vens
Author-email: jj+ialauncher@rtts.eu
License: UNKNOWN
Platform: UNKNOWN
Classifier: Programming Language :: Python :: 3
Classifier: License :: OSI Approved :: GNU General Public License v3 or later (GPLv3+)
Classifier: Operating System :: OS Independent
Requires-Python: >=3.8
